netprobe/__init__.py
netprobe/command.py
netprobe/config.py
netprobe/control.py
netprobe/database.py
netprobe/formatter.py
netprobe/probe.py
netprobe/reporter.py
netprobe/systrol.py
netprobe-1.0.6.dist-info/METADATA
netprobe-1.0.6.dist-info/WHEEL
netprobe-1.0.6.dist-info/entry_points.txt
netprobe-1.0.6.dist-info/top_level.txt
netprobe-1.0.6.dist-info/RECORD
